mnistdet/__init__.py
mnistdet/collation.py
mnistdet/config.py
mnistdet/dataset.py
mnistdet/simulator.py
mnist_detection-0.1.7.dist-info/LICENSE
mnist_detection-0.1.7.dist-info/METADATA
mnist_detection-0.1.7.dist-info/WHEEL
mnist_detection-0.1.7.dist-info/top_level.txt
mnist_detection-0.1.7.dist-info/RECORD
